blockflow/block.py
blockflow/boundary.py
blockflow/dtypes.py
blockflow/errors.py
blockflow/gpt4_tokenizer.json
blockflow/tokenizer.py
blockflow/truncation.py
blockflow-0.0.1.dist-info/LICENSE
blockflow-0.0.1.dist-info/METADATA
blockflow-0.0.1.dist-info/WHEEL
blockflow-0.0.1.dist-info/RECORD
