Metadata-Version: 2.1
Name: blockflow
Version: 0.0.1
Summary: prompt management for llms
License: Apache 2.0
Author: Oluwatobi Adefami
Author-email: tobiadefami@gmail.com
Requires-Python: >=3.10,<3.12
Classifier: License :: Other/Proprietary License
Classifier: Programming Language :: Python :: 3
Classifier: Programming Language :: Python :: 3.10
Classifier: Programming Language :: Python :: 3.11
Requires-Dist: coverage (>=7.3.2,<8.0.0)
Requires-Dist: rich (>=13.6.0,<14.0.0)
Requires-Dist: spacy (>=3.7.2,<4.0.0)
Requires-Dist: tiktoken (>=0.5.1,<0.6.0)
Requires-Dist: transformers (>=4.34.0,<5.0.0)
